.gitignore
MANIFEST.in
README.rst
b.sh
base.cfg
bootstrap.py
buildout.cfg
setup.cfg
setup.py
test-4.0.x.cfg
test-4.1.x.cfg
test-4.2.x.cfg
test-4.3.x.cfg
travis-4.0.x.cfg
travis-4.1.x.cfg
travis-4.2.x.cfg
travis-4.3.x.cfg
version.txt
.cache/303f15aa9e965191a65e6ca13545f47a
.cache/a7c712d65bf4acf314f13927a5059c1e
.cache/ab1b750b567f172c876f0d2e682da199
.cache/d5e9a9999ff8f603cb24cb41ba113c7b
.cache/d701d8c5126dc3da98a4705bda4e900d
.cache/fee93940599fd79bdf7e714f3a706d44
docs/CHANGES.rst
docs/INSTALL.rst
docs/LICENSE.GPL
docs/LICENSE.txt
scripts/sync_from_generic.sh
src/collective/__init__.py
src/collective.datatablesviews.egg-info/PKG-INFO
src/collective.datatablesviews.egg-info/SOURCES.txt
src/collective.datatablesviews.egg-info/dependency_links.txt
src/collective.datatablesviews.egg-info/entry_points.txt
src/collective.datatablesviews.egg-info/namespace_packages.txt
src/collective.datatablesviews.egg-info/requires.txt
src/collective.datatablesviews.egg-info/top_level.txt
src/collective/datatablesviews/__init__.py
src/collective/datatablesviews/app_config.py
src/collective/datatablesviews/configure.zcml
src/collective/datatablesviews/interfaces.py
src/collective/datatablesviews/profiles.zcml
src/collective/datatablesviews/rebuild_i18n.sh
src/collective/datatablesviews/setuphandlers.py
src/collective/datatablesviews/testing.py
src/collective/datatablesviews/version.txt
src/collective/datatablesviews/Extensions/Install.py
src/collective/datatablesviews/Extensions/__init__.py
src/collective/datatablesviews/browser/__init__.py
src/collective/datatablesviews/browser/configure.zcml
src/collective/datatablesviews/browser/datatables_view.pt
src/collective/datatablesviews/browser/view.py
src/collective/datatablesviews/browser/resources/README.txt
src/collective/datatablesviews/browser/resources/table.js
src/collective/datatablesviews/locales/collective.datatablesviews-manual.pot
src/collective/datatablesviews/locales/collective.datatablesviews.pot
src/collective/datatablesviews/locales/fr/LC_MESSAGES/collective.datatablesviews.po
src/collective/datatablesviews/profiles/default/browserlayer.xml
src/collective/datatablesviews/profiles/default/collective.datatablesviews_various.txt
src/collective/datatablesviews/profiles/default/metadata.xml
src/collective/datatablesviews/profiles/default/skins.xml
