Metadata-Version: 1.1
Name: collective.datatablesviews
Version: 1.1
Summary: various datatables views for plone content types (collections atm)
Home-page: http://pypi.python.org/pypi/collective.datatablesviews
Author: kiorky
Author-email: kiorky@cryptelium.net
License: GPL
Platform: UNKNOWN
Classifier: Framework :: Plone
Classifier: Framework :: Plone :: 4.0
Classifier: Framework :: Plone :: 4.1
Classifier: Framework :: Plone :: 4.2
Classifier: Programming Language :: Python
Classifier: Topic :: Software Development
